BetterDebugging/__init__.py
BetterDebugging/logger.py
betterdebugging-1.0.5.dist-info/METADATA
betterdebugging-1.0.5.dist-info/WHEEL
betterdebugging-1.0.5.dist-info/top_level.txt
betterdebugging-1.0.5.dist-info/RECORD
