Metadata-Version: 2.4
Name: BetterDebugging
Version: 1.0.5
Summary: A utility plugin, allowing you to set custom logging levels with colors and microsecond precision
Author: Matthew Boyd
Author-email: MatthewBoyd04@gmail.com
Classifier: Programming Language :: Python :: 3
Classifier: License :: OSI Approved :: MIT License
Classifier: Operating System :: OS Independent
Requires-Dist: colorama
Provides-Extra: dev
Requires-Dist: pytest; extra == "dev"
Requires-Dist: twine; extra == "dev"
Dynamic: author
Dynamic: author-email
Dynamic: classifier
Dynamic: description
Dynamic: description-content-type
Dynamic: provides-extra
Dynamic: requires-dist
Dynamic: summary
